README.md
setup.py
ovos_solver_chatgpt_plugin/__init__.py
ovos_solver_chatgpt_plugin.egg-info/PKG-INFO
ovos_solver_chatgpt_plugin.egg-info/SOURCES.txt
ovos_solver_chatgpt_plugin.egg-info/dependency_links.txt
ovos_solver_chatgpt_plugin.egg-info/entry_points.txt
ovos_solver_chatgpt_plugin.egg-info/requires.txt
ovos_solver_chatgpt_plugin.egg-info/top_level.txt
ovos_solver_chatgpt_plugin.egg-info/zip-safe