Metadata-Version: 2.1
Name: ovos-solver-chatgpt-plugin
Version: 0.0.0
Summary: A question solver plugin for ovos/neon/mycroft
Home-page: https://github.com/OpenVoiceOS/ovos-solver-plugin-chatgpt
Author: jarbasai
Author-email: jarbasai@mailfence.com
License: MIT
Keywords: mycroft plugin utterance fallback query
